scrypter/__init__.py
scrypter/__main__.py
scrypter-1.2.1.dist-info/LICENSE
scrypter-1.2.1.dist-info/METADATA
scrypter-1.2.1.dist-info/WHEEL
scrypter-1.2.1.dist-info/entry_points.txt
scrypter-1.2.1.dist-info/top_level.txt
scrypter-1.2.1.dist-info/RECORD
