Metadata-Version: 2.1
Name: scrypter
Version: 1.2.1
Summary: An translator.
Home-page: https://github.com/sevenc-nanashi/scrypter
Author: sevenc_nanashi
License: UNKNOWN
Platform: UNKNOWN
Classifier: Programming Language :: Python :: 3.8
Classifier: License :: OSI Approved :: MIT License
Classifier: Operating System :: OS Independent
Requires-Dist: readchar
Requires-Dist: pyperclip
Requires-Dist: wxPython
